tyro/__init__.py
tyro/_arguments.py
tyro/_calling.py
tyro/_cli.py
tyro/_deprecated.py
tyro/_docstrings.py
tyro/_fields.py
tyro/_fmtlib.py
tyro/_parsers.py
tyro/_resolver.py
tyro/_settings.py
tyro/_singleton.py
tyro/_strings.py
tyro/_subcommand_matching.py
tyro/_typing.py
tyro/_typing_compat.py
tyro/_unsafe_cache.py
tyro/_warnings.py
tyro/py.typed
tyro/_backends/__init__.py
tyro/_backends/_argparse.py
tyro/_backends/_argparse_backend.py
tyro/_backends/_argparse_formatter.py
tyro/_backends/_argparse_help_formatting.py
tyro/_backends/_base.py
tyro/_backends/_tyro_backend.py
tyro/_backends/_tyro_help_formatting.py
tyro/_backends/_completion/__init__.py
tyro/_backends/_completion/_base.py
tyro/_backends/_completion/_completion_script.py
tyro/_backends/_completion/_python_completer.py
tyro/_backends/_completion/_spec.py
tyro/_backends/_completion/_tyro_bash.py
tyro/_backends/_completion/_tyro_zsh.py
tyro/conf/__init__.py
tyro/conf/_confstruct.py
tyro/conf/_markers.py
tyro/conf/_mutex_group.py
tyro/constructors/__init__.py
tyro/constructors/_backtracking.py
tyro/constructors/_primitive_spec.py
tyro/constructors/_registry.py
tyro/constructors/_struct_spec.py
tyro/constructors/_struct_spec_attrs.py
tyro/constructors/_struct_spec_dataclass.py
tyro/constructors/_struct_spec_flax.py
tyro/constructors/_struct_spec_ml_collections.py
tyro/constructors/_struct_spec_msgspec.py
tyro/constructors/_struct_spec_pydantic.py
tyro/extras/__init__.py
tyro/extras/_base_configs.py
tyro/extras/_choices_type.py
tyro/extras/_serialization.py
tyro/extras/_subcommand_app.py
tyro/extras/_subcommand_cli_from_dict.py
tyro-1.0.3.dist-info/METADATA
tyro-1.0.3.dist-info/WHEEL
tyro-1.0.3.dist-info/licenses/LICENSE
tyro-1.0.3.dist-info/RECORD
