Metadata-Version: 2.4
Name: tyro
Version: 1.0.3
Summary: CLI interfaces & config objects, from types
Project-URL: GitHub, https://github.com/brentyi/tyro
Author-email: brentyi <brentyi@berkeley.edu>
License: MIT
License-File: LICENSE
Classifier: License :: OSI Approved :: MIT License
Classifier: Operating System :: OS Independent
Classifier: Programming Language :: Python :: 3
Classifier: Programming Language :: Python :: 3.8
Classifier: Programming Language :: Python :: 3.9
Classifier: Programming Language :: Python :: 3.10
Classifier: Programming Language :: Python :: 3.11
Classifier: Programming Language :: Python :: 3.12
Classifier: Programming Language :: Python :: 3.13
Classifier: Programming Language :: Python :: 3.14
Requires-Python: >=3.8
Requires-Dist: docstring-parser>=0.15
Requires-Dist: eval-type-backport>=0.1.3; python_version < '3.10'
Requires-Dist: typeguard>=4.0.0
Requires-Dist: typing-extensions>=4.13.0
Provides-Extra: dev
Requires-Dist: attrs>=21.4.0; extra == 'dev'
Requires-Dist: coverage[toml]>=6.5.0; extra == 'dev'
Requires-Dist: eval-type-backport>=0.1.3; extra == 'dev'
Requires-Dist: ml-collections>=0.1.0; extra == 'dev'
Requires-Dist: msgspec>=0.18.6; extra == 'dev'
Requires-Dist: mypy>=1.4.1; extra == 'dev'
Requires-Dist: omegaconf>=2.2.2; extra == 'dev'
Requires-Dist: pydantic!=2.10.0,>=2.5.2; extra == 'dev'
Requires-Dist: pyright!=1.1.379,>=1.1.349; extra == 'dev'
Requires-Dist: pytest-cov>=3.0.0; extra == 'dev'
Requires-Dist: pytest-xdist>=3.5.0; extra == 'dev'
Requires-Dist: pytest>=7.1.2; extra == 'dev'
Requires-Dist: pyyaml>=6.0; extra == 'dev'
Requires-Dist: shtab>=1.5.6; extra == 'dev'
Requires-Dist: universal-pathlib>=0.2.0; extra == 'dev'
Provides-Extra: dev-nn
Requires-Dist: attrs>=21.4.0; extra == 'dev-nn'
Requires-Dist: coverage[toml]>=6.5.0; extra == 'dev-nn'
Requires-Dist: eval-type-backport>=0.1.3; extra == 'dev-nn'
Requires-Dist: flax>=0.6.9; (python_version <= '3.13') and extra == 'dev-nn'
Requires-Dist: ml-collections>=0.1.0; extra == 'dev-nn'
Requires-Dist: msgspec>=0.18.6; extra == 'dev-nn'
Requires-Dist: mypy>=1.4.1; extra == 'dev-nn'
Requires-Dist: numpy>=1.20.0; extra == 'dev-nn'
Requires-Dist: omegaconf>=2.2.2; extra == 'dev-nn'
Requires-Dist: pydantic!=2.10.0,>=2.5.2; extra == 'dev-nn'
Requires-Dist: pyright!=1.1.379,>=1.1.349; extra == 'dev-nn'
Requires-Dist: pytest-cov>=3.0.0; extra == 'dev-nn'
Requires-Dist: pytest-xdist>=3.5.0; extra == 'dev-nn'
Requires-Dist: pytest>=7.1.2; extra == 'dev-nn'
Requires-Dist: pyyaml>=6.0; extra == 'dev-nn'
Requires-Dist: shtab>=1.5.6; extra == 'dev-nn'
Requires-Dist: torch>=1.10.0; (python_version >= '3.9' and python_version <= '3.13') and extra == 'dev-nn'
Requires-Dist: universal-pathlib>=0.2.0; extra == 'dev-nn'
